QMon-0.1.1.dist-info/DESCRIPTION.rst
QMon-0.1.1.dist-info/METADATA
QMon-0.1.1.dist-info/RECORD
QMon-0.1.1.dist-info/WHEEL
QMon-0.1.1.dist-info/entry_points.txt
QMon-0.1.1.dist-info/metadata.json
QMon-0.1.1.dist-info/top_level.txt
qmon/__init__.py
qmon/main.py
qmon/monitor.py
qmon/status.py
