Metadata-Version: 2.0
Name: QMon
Version: 0.1.1
Summary: Redis Monitor - monitor number of items and more for any type of redis queue
Home-page: https://github.com/shubhamchaudhary/qmon
Author: Shubham Chaudhary
Author-email: me@shubhamchaudhary.in
License: GPLv3+
Platform: UNKNOWN
Requires-Dist: click (==6.7)
Requires-Dist: hiredis (==0.2.0)
Requires-Dist: hypchat (==0.21)
Requires-Dist: redis (==2.10.5)
